setup.cfg
setup.py
threads/__init__.py
threads/threadDotCount.py
threads/threadSchedule.py
tvdoon/__init__.py
tvdoon/tvdoon
tvdoon.egg-info/PKG-INFO
tvdoon.egg-info/SOURCES.txt
tvdoon.egg-info/dependency_links.txt
tvdoon.egg-info/requires.txt
tvdoon.egg-info/top_level.txt
utility/__init__.py
utility/colors.py
utility/constants.py
utility/fileUtil.py
utility/tvMazeUtil.py