Metadata-Version: 1.1
Name: tvdoon
Version: 1.3.0
Summary: Show Information About Tv Show's, Ratings And So Many Cool Features!
Home-page: https://github.com/LinArcX/tvdoon
Author: LinArcX
Author-email: linarcx@gmail.com
License:  GPLv3
Download-URL: https://github.com/LinArcX/tvdoon/archive/1.3.0.tar.gz
Keywords: tvShow,upcoming tvShow
Platform: UNKNOWN
Classifier: Development Status :: 3 - Alpha
Classifier: Topic :: Utilities
Classifier: Programming Language :: Python :: 3.6
Classifier: License :: OSI Approved :: GNU General Public License v3 (GPLv3)
